{
	"configurations" : 
	[
		{
			"directories" : 
			[
				{
					"build" : ".",
					"childIndexes" : 
					[
						1,
						2,
						4,
						6,
						7
					],
					"jsonFile" : "directory-.-Debug-f5ebdc15457944623624.json",
					"minimumCMakeVersion" : 
					{
						"string" : "3.18"
					},
					"projectIndex" : 0,
					"source" : ".",
					"targetIndexes" : 
					[
						0
					]
				},
				{
					"build" : "libs/glad",
					"jsonFile" : "directory-libs.glad-Debug-ca06ba1f4a1543a5a943.json",
					"minimumCMakeVersion" : 
					{
						"string" : "3.18"
					},
					"parentIndex" : 0,
					"projectIndex" : 0,
					"source" : "libs/glad",
					"targetIndexes" : 
					[
						1
					]
				},
				{
					"build" : "libs/glfw",
					"childIndexes" : 
					[
						3
					],
					"jsonFile" : "directory-libs.glfw-Debug-f3d5a33885c87b28e9d1.json",
					"minimumCMakeVersion" : 
					{
						"string" : "3.0"
					},
					"parentIndex" : 0,
					"projectIndex" : 1,
					"source" : "libs/glfw"
				},
				{
					"build" : "libs/glfw/src",
					"jsonFile" : "directory-libs.glfw.src-Debug-f41b39c9303265a24a65.json",
					"minimumCMakeVersion" : 
					{
						"string" : "3.0"
					},
					"parentIndex" : 2,
					"projectIndex" : 1,
					"source" : "libs/glfw/src",
					"targetIndexes" : 
					[
						2,
						4
					]
				},
				{
					"build" : "libs/glm",
					"childIndexes" : 
					[
						5
					],
					"jsonFile" : "directory-libs.glm-Debug-44c86d80c1bd93f510b3.json",
					"minimumCMakeVersion" : 
					{
						"string" : "3.2"
					},
					"parentIndex" : 0,
					"projectIndex" : 2,
					"source" : "libs/glm"
				},
				{
					"build" : "libs/glm/glm",
					"jsonFile" : "directory-libs.glm.glm-Debug-cdeeb9f9b6cfd4b776d1.json",
					"minimumCMakeVersion" : 
					{
						"string" : "3.2"
					},
					"parentIndex" : 4,
					"projectIndex" : 2,
					"source" : "libs/glm/glm"
				},
				{
					"build" : "libs/stb",
					"jsonFile" : "directory-libs.stb-Debug-999db47acc2e288e6620.json",
					"minimumCMakeVersion" : 
					{
						"string" : "3.18"
					},
					"parentIndex" : 0,
					"projectIndex" : 0,
					"source" : "libs/stb"
				},
				{
					"build" : "libs/spdlog",
					"jsonFile" : "directory-libs.spdlog-Debug-768e61a1fd9f9758ddd3.json",
					"minimumCMakeVersion" : 
					{
						"string" : "3.10"
					},
					"parentIndex" : 0,
					"projectIndex" : 3,
					"source" : "libs/spdlog",
					"targetIndexes" : 
					[
						3
					]
				}
			],
			"name" : "Debug",
			"projects" : 
			[
				{
					"childIndexes" : 
					[
						1,
						2,
						3
					],
					"directoryIndexes" : 
					[
						0,
						1,
						6
					],
					"name" : "blueberry",
					"targetIndexes" : 
					[
						0,
						1
					]
				},
				{
					"directoryIndexes" : 
					[
						2,
						3
					],
					"name" : "GLFW",
					"parentIndex" : 0,
					"targetIndexes" : 
					[
						2,
						4
					]
				},
				{
					"directoryIndexes" : 
					[
						4,
						5
					],
					"name" : "glm",
					"parentIndex" : 0
				},
				{
					"directoryIndexes" : 
					[
						7
					],
					"name" : "spdlog",
					"parentIndex" : 0,
					"targetIndexes" : 
					[
						3
					]
				}
			],
			"targets" : 
			[
				{
					"directoryIndex" : 0,
					"id" : "blueberry::@6890427a1f51a3e7e1df",
					"jsonFile" : "target-blueberry-Debug-4880ae22299618e31999.json",
					"name" : "blueberry",
					"projectIndex" : 0
				},
				{
					"directoryIndex" : 1,
					"id" : "glad::@394eb3637a8e70cb7dd5",
					"jsonFile" : "target-glad-Debug-bf4b0a4c8ea219af9971.json",
					"name" : "glad",
					"projectIndex" : 0
				},
				{
					"directoryIndex" : 3,
					"id" : "glfw::@9d94ad66e13f8aab41f7",
					"jsonFile" : "target-glfw-Debug-ce6bc4885edc33806a17.json",
					"name" : "glfw",
					"projectIndex" : 1
				},
				{
					"directoryIndex" : 7,
					"id" : "spdlog::@f9417c48a877073874e9",
					"jsonFile" : "target-spdlog-Debug-46d488869ed5269f9686.json",
					"name" : "spdlog",
					"projectIndex" : 3
				},
				{
					"directoryIndex" : 3,
					"id" : "update_mappings::@9d94ad66e13f8aab41f7",
					"jsonFile" : "target-update_mappings-Debug-98647b82fca646a83ed6.json",
					"name" : "update_mappings",
					"projectIndex" : 1
				}
			]
		}
	],
	"kind" : "codemodel",
	"paths" : 
	{
		"build" : "/home/shadow_acolyte/dev/blueberry-engine/build",
		"source" : "/home/shadow_acolyte/dev/blueberry-engine"
	},
	"version" : 
	{
		"major" : 2,
		"minor" : 3
	}
}
